rss_distributions/Binomialdistribution.py
rss_distributions/Gaussiandistribution.py
rss_distributions/Generaldistribution.py
rss_distributions/__init__.py
rss_distributions-0.1.dist-info/DESCRIPTION.rst
rss_distributions-0.1.dist-info/METADATA
rss_distributions-0.1.dist-info/RECORD
rss_distributions-0.1.dist-info/WHEEL
rss_distributions-0.1.dist-info/metadata.json
rss_distributions-0.1.dist-info/top_level.txt
