Metadata-Version: 2.0
Name: rss-distributions
Version: 0.1
Summary: Gaussian and binomial distributions
Home-page: UNKNOWN
Author: Rachneet Singh Sachdeva
Author-email: rachneetsachdeva@yahoo.com
License: UNKNOWN
Platform: UNKNOWN
